otrs_somconnexio/__init__.py
otrs_somconnexio/client.py
otrs_somconnexio/exceptions.py
otrs_somconnexio/otrs_models/__init__.py
otrs_somconnexio/otrs_models/abstract_article.py
otrs_somconnexio/otrs_models/adsl_data.py
otrs_somconnexio/otrs_models/adsl_dynamic_fields.py
otrs_somconnexio/otrs_models/adsl_ticket.py
otrs_somconnexio/otrs_models/coverage_article.py
otrs_somconnexio/otrs_models/coverage_ticket.py
otrs_somconnexio/otrs_models/customer_data.py
otrs_somconnexio/otrs_models/customer_user.py
otrs_somconnexio/otrs_models/fiber_data.py
otrs_somconnexio/otrs_models/fiber_dynamic_fields.py
otrs_somconnexio/otrs_models/fiber_ticket.py
otrs_somconnexio/otrs_models/internet_data.py
otrs_somconnexio/otrs_models/internet_dynamic_fields.py
otrs_somconnexio/otrs_models/mobile_data.py
otrs_somconnexio/otrs_models/mobile_dynamic_fields.py
otrs_somconnexio/otrs_models/mobile_ticket.py
otrs_somconnexio/otrs_models/providers.py
otrs_somconnexio/otrs_models/provision_article.py
otrs_somconnexio/otrs_models/provision_dynamic_fields.py
otrs_somconnexio/otrs_models/provision_ticket.py
otrs_somconnexio/otrs_models/responsible_data.py
otrs_somconnexio/otrs_models/router_4G_data.py
otrs_somconnexio/otrs_models/router_4G_dynamic_fields.py
otrs_somconnexio/otrs_models/router_4G_ticket.py
otrs_somconnexio/otrs_models/service.py
otrs_somconnexio/otrs_models/switchboard_data.py
otrs_somconnexio/otrs_models/switchboard_dynamic_fields.py
otrs_somconnexio/otrs_models/switchboard_header_data.py
otrs_somconnexio/otrs_models/switchboard_header_dynamic_fields.py
otrs_somconnexio/otrs_models/switchboard_header_ticket.py
otrs_somconnexio/otrs_models/switchboard_ticket.py
otrs_somconnexio/otrs_models/telecom_company.py
otrs_somconnexio/otrs_models/ticket_factory.py
otrs_somconnexio/otrs_models/vf_provisioning_article.py
otrs_somconnexio/otrs_models/configurations/__init__.py
otrs_somconnexio/otrs_models/configurations/changes/__init__.py
otrs_somconnexio-0.7.3.dist-info/METADATA
otrs_somconnexio-0.7.3.dist-info/WHEEL
otrs_somconnexio-0.7.3.dist-info/top_level.txt
otrs_somconnexio-0.7.3.dist-info/RECORD
