Metadata-Version: 2.1
Name: otrs-somconnexio
Version: 0.7.3
Summary: Python package for Somconnexio data syncing in OTRS
Home-page: https://gitlab.com/coopdevs/otrs_somconnexio
Author: Coopdevs
Author-email: info@coopdevs.org
License: UNKNOWN
Platform: UNKNOWN
Classifier: Development Status :: 3 - Alpha
Classifier: Operating System :: POSIX :: Linux
Classifier: Programming Language :: Python :: 2
Classifier: Programming Language :: Python :: 2.7
Requires-Dist: pyotrs==0.12.7
Requires-Dist: future==0.18.2
